__init__.py
nftables.py
pip_nftables-1.0.9.post1.dist-info/LICENSE
pip_nftables-1.0.9.post1.dist-info/METADATA
pip_nftables-1.0.9.post1.dist-info/WHEEL
pip_nftables-1.0.9.post1.dist-info/top_level.txt
pip_nftables-1.0.9.post1.dist-info/RECORD
