Metadata-Version: 2.1
Name: pip-nftables
Version: 1.0.9.post1
Summary: Copy of the python3-nftables module used to interact with libnftables
Home-page: https://github.com/felipequecole/python3-nftables
Author: Felipe Quecole
Author-email: felipequecole@gmail.com
Project-URL: Repository, https://github.com/felipequecole/python3-nftables
Project-URL: Bug Tracker, https://github.com/felipequecole/python3-nftables/issues
Classifier: Programming Language :: Python :: 3
Classifier: License :: OSI Approved :: GNU General Public License v2 (GPLv2)
Classifier: Operating System :: OS Independent
Requires-Python: >=3
License-File: LICENSE
